fp_associativity_analyzer/__init__.py
fp_associativity_analyzer/main.py
fp_associativity_analyzer/prompts.py
fp_associativity_analyzer-2025.12.21134137.dist-info/METADATA
fp_associativity_analyzer-2025.12.21134137.dist-info/WHEEL
fp_associativity_analyzer-2025.12.21134137.dist-info/top_level.txt
fp_associativity_analyzer-2025.12.21134137.dist-info/RECORD
