Metadata-Version: 2.4
Name: fp-associativity-analyzer
Version: 2025.12.21134137
Summary: A new package that takes a user's text input about floating-point arithmetic or SIMD programming challenges and returns a structured analysis of potential associativity issues. It uses an LLM to gener
Author-email: fp-associativity-analyzer <hi@eugene.plus>
License: MIT
Project-URL: Homepage, https://github.com/chigwell/fp-associativity-analyzer
Requires-Python: >=3.9
Requires-Dist: langchain-llm7>=0.0.0
Requires-Dist: llmatch-messages>=0.0.0
Requires-Dist: langchain-core>=0.3.0
